odoo10_addon_account_asset_analytic-10.0.1.0.2-py2.7-nspkg.pth
odoo/addons/account_asset_analytic/README.rst
odoo/addons/account_asset_analytic/__init__.py
odoo/addons/account_asset_analytic/__manifest__.py
odoo/addons/account_asset_analytic/i18n/account_asset_analytic.pot
odoo/addons/account_asset_analytic/i18n/ar.po
odoo/addons/account_asset_analytic/i18n/bs.po
odoo/addons/account_asset_analytic/i18n/ca.po
odoo/addons/account_asset_analytic/i18n/cs.po
odoo/addons/account_asset_analytic/i18n/cs_CZ.po
odoo/addons/account_asset_analytic/i18n/de.po
odoo/addons/account_asset_analytic/i18n/en_GB.po
odoo/addons/account_asset_analytic/i18n/es.po
odoo/addons/account_asset_analytic/i18n/es_CO.po
odoo/addons/account_asset_analytic/i18n/es_CR.po
odoo/addons/account_asset_analytic/i18n/es_EC.po
odoo/addons/account_asset_analytic/i18n/es_MX.po
odoo/addons/account_asset_analytic/i18n/es_PA.po
odoo/addons/account_asset_analytic/i18n/es_VE.po
odoo/addons/account_asset_analytic/i18n/et.po
odoo/addons/account_asset_analytic/i18n/fi.po
odoo/addons/account_asset_analytic/i18n/fr.po
odoo/addons/account_asset_analytic/i18n/fr_CH.po
odoo/addons/account_asset_analytic/i18n/gl.po
odoo/addons/account_asset_analytic/i18n/hr.po
odoo/addons/account_asset_analytic/i18n/hr_HR.po
odoo/addons/account_asset_analytic/i18n/hu.po
odoo/addons/account_asset_analytic/i18n/it.po
odoo/addons/account_asset_analytic/i18n/ja.po
odoo/addons/account_asset_analytic/i18n/lt.po
odoo/addons/account_asset_analytic/i18n/mk.po
odoo/addons/account_asset_analytic/i18n/mn.po
odoo/addons/account_asset_analytic/i18n/nb.po
odoo/addons/account_asset_analytic/i18n/nl.po
odoo/addons/account_asset_analytic/i18n/nl_BE.po
odoo/addons/account_asset_analytic/i18n/nl_NL.po
odoo/addons/account_asset_analytic/i18n/pl.po
odoo/addons/account_asset_analytic/i18n/pt.po
odoo/addons/account_asset_analytic/i18n/pt_BR.po
odoo/addons/account_asset_analytic/i18n/pt_PT.po
odoo10_addon_account_asset_analytic-10.0.1.0.2.dist-info/METADATA
odoo10_addon_account_asset_analytic-10.0.1.0.2.dist-info/RECORD
odoo10_addon_account_asset_analytic-10.0.1.0.2.dist-info/WHEEL
odoo10_addon_account_asset_analytic-10.0.1.0.2.dist-info/namespace_packages.txt
odoo10_addon_account_asset_analytic-10.0.1.0.2.dist-info/top_level.txt
